netbox_tunnels2/__init__.py
netbox_tunnels2/admin.py
netbox_tunnels2/constants.py
netbox_tunnels2/filtersets.py
netbox_tunnels2/forms.py
netbox_tunnels2/graphql.py
netbox_tunnels2/models.py
netbox_tunnels2/navigation.py
netbox_tunnels2/search.py
netbox_tunnels2/tables.py
netbox_tunnels2/template_content.py
netbox_tunnels2/urls.py
netbox_tunnels2/version.py
netbox_tunnels2/views.py
netbox_tunnels2/api/__init__.py
netbox_tunnels2/api/serializers.py
netbox_tunnels2/api/urls.py
netbox_tunnels2/api/views.py
netbox_tunnels2/migrations/0001_initial.py
netbox_tunnels2/migrations/0002_alter_tunnel_b_pub_address.py
netbox_tunnels2/migrations/0003_tunnel_tenant.py
netbox_tunnels2/migrations/0004_alter_tunnel_side_a_assigned_object_type_and_more.py
netbox_tunnels2/migrations/0005_alter_tunnel.py
netbox_tunnels2/migrations/__init__.py
netbox_tunnels2/templates/netbox_tunnels2/interface_extend.html
netbox_tunnels2/templates/netbox_tunnels2/plugintunnel.html
netbox_tunnels2/templates/netbox_tunnels2/plugintunnel_edit.html
netbox_tunnels2/templates/netbox_tunnels2/tunnel.html
netbox_tunnels2/templates/netbox_tunnels2/tunnel_edit.html
netbox_tunnels2/templates/netbox_tunnels2/tunneltype.html
netbox_tunnels2/tests/__init__.py
netbox_tunnels2/tests/custom.py
netbox_tunnels2/tests/test_api.py
netbox_tunnels2/tests/test_models.py
netbox_tunnels2-0.2.9.dist-info/LICENSE
netbox_tunnels2-0.2.9.dist-info/METADATA
netbox_tunnels2-0.2.9.dist-info/WHEEL
netbox_tunnels2-0.2.9.dist-info/top_level.txt
netbox_tunnels2-0.2.9.dist-info/RECORD
