Metadata-Version: 2.1
Name: netbox-tunnels2
Version: 0.2.9
Summary: Provides the ability track IP Tunnels.
Home-page: https://github.com/robertlynch3/netbox-tunnels2
Author: Robert Lynch
Author-email: Robert Lynch <robertlynch3@users.noreply.github.com>
License: Apache License
Project-URL: Homepage, https://github.com/robertlynch3/netbox-tunnels2
License-File: LICENSE
Provides-Extra: dev
Requires-Dist: black ; extra == 'dev'
Requires-Dist: bumpver ; extra == 'dev'
Requires-Dist: isort ; extra == 'dev'
Requires-Dist: pip-tools ; extra == 'dev'
Requires-Dist: pytest ; extra == 'dev'
